issueup/__init__.py
issueup-0.1.0.dist-info/entry_points.txt
issueup-0.1.0.dist-info/LICENSE
issueup-0.1.0.dist-info/WHEEL
issueup-0.1.0.dist-info/METADATA
issueup-0.1.0.dist-info/RECORD
